MANIFEST.in
README.md
setup.cfg
setup.py
xlsapi/__init__.py
xlsapi/demo.py
xlsapi/files.py
xlsapi/notification.py
xlsapi/server.py
xlsapi/swagger.py
xlsapi/xlsreader.py
xlsapi.egg-info/PKG-INFO
xlsapi.egg-info/SOURCES.txt
xlsapi.egg-info/dependency_links.txt
xlsapi.egg-info/requires.txt
xlsapi.egg-info/top_level.txt