Metadata-Version: 1.1
Name: xlsapi
Version: 0.1.0
Summary: serve XLS files as REST api
Home-page: https://gitlab.com/irgangla/xlsapi
Author: Thomas Irgang
Author-email: thomas@irgang-la.de
License: UNKNOWN
Download-URL: https://gitlab.com/irgangla/xlsapi/archive/v0.1.0.tar.gz
Keywords: XLS,Excel,REST,API
Platform: UNKNOWN
Classifier: Programming Language :: Python
Classifier: Programming Language :: Python :: 3
Classifier: Development Status :: 4 - Beta
Classifier: Environment :: Other Environment
Classifier: Intended Audience :: Developers
Classifier: License :: OSI Approved :: MIT License
Classifier: Programming Language :: Python :: 3
Classifier: Programming Language :: Python :: 3.7
Classifier: Operating System :: OS Independent
